riid/__init__.py
riid/anomaly.py
riid/metrics.py
riid/visualize.py
riid/data/__init__.py
riid/data/labeling.py
riid/data/sampleset.py
riid/data/converters/__init__.py
riid/data/converters/aipt.py
riid/data/converters/topcoder.py
riid/data/synthetic/__init__.py
riid/data/synthetic/passby.py
riid/data/synthetic/seed.py
riid/data/synthetic/static.py
riid/gadras/__init__.py
riid/gadras/api.py
riid/gadras/api_schema.json
riid/gadras/pcf.py
riid/losses/__init__.py
riid/losses/sparsemax.py
riid/models/__init__.py
riid/models/bayes.py
riid/models/neural_nets/__init__.py
riid/models/neural_nets/arad.py
riid-2.1.0.dist-info/LICENSE.md
riid-2.1.0.dist-info/METADATA
riid-2.1.0.dist-info/NOTICE.md
riid-2.1.0.dist-info/WHEEL
riid-2.1.0.dist-info/top_level.txt
riid-2.1.0.dist-info/RECORD
