Metadata-Version: 2.1
Name: riid
Version: 2.1.0
Summary: Machine learning-based models and utilities for radioisotope identification
Author: Tyler Morrow, Nathan Price, Travis McGuire, Tyler Ganter, Aislinn Handley, Paul Thelen, Alan Van Omen, Leon Ross, Alyshia Bustos
Maintainer-email: Tyler Morrow <tmorro@sandia.gov>
License: # BSD 3-Clause License
Project-URL: repository, https://github.com/sandialabs/PyRIID
Keywords: pyriid,riid,machine learning,radioisotope identification,gamma spectrum
Classifier: Development Status :: 5 - Production/Stable
Classifier: Intended Audience :: Developers
Classifier: Intended Audience :: Education
Classifier: Intended Audience :: Science/Research
Classifier: License :: OSI Approved :: BSD License
Classifier: Topic :: Scientific/Engineering
Classifier: Topic :: Scientific/Engineering :: Mathematics
Classifier: Topic :: Scientific/Engineering :: Artificial Intelligence
Classifier: Topic :: Software Development
Classifier: Topic :: Software Development :: Libraries
Classifier: Topic :: Software Development :: Libraries :: Python Modules
Classifier: Programming Language :: Python :: 3
Classifier: Programming Language :: Python :: 3 :: Only
Classifier: Programming Language :: Python :: 3.8
Classifier: Programming Language :: Python :: 3.9
Classifier: Programming Language :: Python :: 3.10
Requires-Python: <3.11,>=3.8
License-File: LICENSE.md
License-File: NOTICE.md
Requires-Dist: jsonschema==4.17.*
Requires-Dist: matplotlib==3.7.*
Requires-Dist: pyyaml==6.0.*
Requires-Dist: seaborn==0.12.*
Requires-Dist: tf2onnx==1.14.*
Requires-Dist: onnx==1.14.1
Requires-Dist: tqdm==4.65.*
Requires-Dist: numpy==1.23.*
Requires-Dist: pandas==2.0.*
Requires-Dist: parmap==1.6.*
Requires-Dist: tables==3.8.*
Requires-Dist: tensorflow==2.12.*
Requires-Dist: tensorflow-io==0.27.*
Requires-Dist: tensorflow-model-optimization==0.7.*
Requires-Dist: tensorflow-probability==0.20.*
Requires-Dist: typeguard==2.7.*
Requires-Dist: scikit-learn==1.2.*
Requires-Dist: pythonnet==3.0.*; platform_system == "Windows"
Provides-Extra: dev
Requires-Dist: flake8; extra == "dev"
Requires-Dist: flake8-quotes; extra == "dev"
Requires-Dist: coverage; extra == "dev"
Requires-Dist: ipykernel; extra == "dev"
Requires-Dist: tabulate; extra == "dev"
